{"info":{"file":"/home/vagrant/projects/instrumental/src/components/CustomField/YouTubeLink.js","fileShort":"rc/components/CustomField/YouTubeLink.js","fileSafe":"rc_components_CustomField_YouTubeLink_js","link":"files/rc_components_CustomField_YouTubeLink_js/index.html"},"complexity":{"methodAggregate":{"cyclomatic":4,"cyclomaticDensity":14.815,"halstead":{"bugs":0.525,"difficulty":21.89,"effort":34458.098,"length":249,"time":1914.339,"vocabulary":80,"volume":1574.16,"operands":{"distinct":59,"total":123,"identifiers":["__stripped__"]},"operators":{"distinct":21,"total":126,"identifiers":["__stripped__"]}},"params":4,"sloc":{"logical":27,"physical":80}},"settings":{"commonjs":false,"forin":false,"logicalor":true,"switchcase":true,"trycatch":false,"newmi":true},"classes":[{"methodAggregate":{"cyclomatic":4,"cyclomaticDensity":16,"halstead":{"bugs":0.406,"difficulty":16.667,"effort":20300,"length":203,"time":1127.778,"vocabulary":64,"volume":1218,"operands":{"distinct":48,"total":100,"identifiers":["__stripped__"]},"operators":{"distinct":16,"total":103,"identifiers":["__stripped__"]}},"params":4,"sloc":{"logical":25,"physical":68}},"errors":[],"lineEnd":77,"lineStart":10,"methods":[{"cyclomatic":1,"cyclomaticDensity":33.333,"halstead":{"bugs":0.038,"difficulty":4,"effort":453.199,"length":29,"time":25.178,"vocabulary":15,"volume":113.3,"operands":{"distinct":9,"total":12,"identifiers":["__stripped__"]},"operators":{"distinct":6,"total":17,"identifiers":["__stripped__"]}},"params":1,"sloc":{"logical":3,"physical":6},"errors":[],"lineEnd":27,"lineStart":22,"name":"constructor","complexity":{"cyclomatic":1,"sloc":{"logical":3,"physical":6},"halstead":{"bugs":0.038,"difficulty":4,"effort":453.199,"length":29,"time":25.178,"vocabulary":15,"volume":113.3,"operands":{"distinct":9,"total":12,"identifiers":["__stripped__"]},"operators":{"distinct":6,"total":17,"identifiers":["__stripped__"]}}},"line":22},{"cyclomatic":3,"cyclomaticDensity":60,"halstead":{"bugs":0.043,"difficulty":9.375,"effort":1211.884,"length":31,"time":67.327,"vocabulary":18,"volume":129.268,"operands":{"distinct":8,"total":15,"identifiers":["__stripped__"]},"operators":{"distinct":10,"total":16,"identifiers":["__stripped__"]}},"params":1,"sloc":{"logical":5,"physical":7},"errors":[],"lineEnd":35,"lineStart":29,"name":"parseUrl","complexity":{"cyclomatic":3,"sloc":{"logical":5,"physical":7},"halstead":{"bugs":0.043,"difficulty":9.375,"effort":1211.884,"length":31,"time":67.327,"vocabulary":18,"volume":129.268,"operands":{"distinct":8,"total":15,"identifiers":["__stripped__"]},"operators":{"distinct":10,"total":16,"identifiers":["__stripped__"]}}},"line":29},{"cyclomatic":2,"cyclomaticDensity":22.222,"halstead":{"bugs":0.145,"difficulty":7.308,"effort":3173.539,"length":84,"time":176.308,"vocabulary":36,"volume":434.274,"operands":{"distinct":26,"total":38,"identifiers":["__stripped__"]},"operators":{"distinct":10,"total":46,"identifiers":["__stripped__"]}},"params":0,"sloc":{"logical":9,"physical":40},"errors":[],"lineEnd":76,"lineStart":37,"name":"render","complexity":{"cyclomatic":2,"sloc":{"logical":9,"physical":40},"halstead":{"bugs":0.145,"difficulty":7.308,"effort":3173.539,"length":84,"time":176.308,"vocabulary":36,"volume":434.274,"operands":{"distinct":26,"total":38,"identifiers":["__stripped__"]},"operators":{"distinct":10,"total":46,"identifiers":["__stripped__"]}}},"line":37},{"cyclomatic":1,"cyclomaticDensity":0,"halstead":{"bugs":0.006,"difficulty":2,"effort":36.189,"length":7,"time":2.011,"vocabulary":6,"volume":18.095,"operands":{"distinct":3,"total":4,"identifiers":["__stripped__"]},"operators":{"distinct":3,"total":3,"identifiers":["__stripped__"]}},"params":2,"sloc":{"logical":0,"physical":1},"errors":[],"lineEnd":54,"lineStart":54,"name":"<anonymous>","complexity":{"cyclomatic":1,"sloc":{"logical":0,"physical":1},"halstead":{"bugs":0.006,"difficulty":2,"effort":36.189,"length":7,"time":2.011,"vocabulary":6,"volume":18.095,"operands":{"distinct":3,"total":4,"identifiers":["__stripped__"]},"operators":{"distinct":3,"total":3,"identifiers":["__stripped__"]}}},"line":54}],"methodAverage":{"cyclomatic":1.75,"cyclomaticDensity":28.889,"halstead":{"bugs":0.058,"difficulty":5.671,"effort":1218.703,"length":37.75,"time":67.706,"vocabulary":18.75,"volume":173.734,"operands":{"distinct":11.5,"total":17.25},"operators":{"distinct":7.25,"total":20.5}},"params":1,"sloc":{"logical":4.25,"physical":13.5}},"name":"RenderCustomYouTubeLink","maintainability":72.006}],"dependencies":[{"line":1,"path":"react","type":"esm"},{"line":2,"path":"prop-types","type":"esm"},{"line":3,"path":"lodash","type":"esm"},{"line":4,"path":"react-foundation","type":"esm"},{"line":5,"path":"../Field","type":"esm"},{"line":6,"path":"redux-form","type":"esm"}],"errors":[],"lineEnd":80,"lineStart":1,"maintainability":72.006,"methods":[],"methodAverage":{"cyclomatic":1.75,"cyclomaticDensity":28.889,"halstead":{"bugs":0.058,"difficulty":5.671,"effort":1218.703,"length":37.75,"time":67.706,"vocabulary":18.75,"volume":173.734,"operands":{"distinct":11.5,"total":17.25},"operators":{"distinct":7.25,"total":20.5}},"params":1,"sloc":{"logical":4.25,"physical":13.5}},"module":"rc/components/CustomField/YouTubeLink.js","aggregate":{"complexity":{"cyclomatic":4,"cyclomaticDensity":14.815,"halstead":{"bugs":0.525,"difficulty":21.89,"effort":34458.098,"length":249,"time":1914.339,"vocabulary":80,"volume":1574.16,"operands":{"distinct":59,"total":123,"identifiers":["__stripped__"]},"operators":{"distinct":21,"total":126,"identifiers":["__stripped__"]}},"params":4,"sloc":{"logical":27,"physical":80}}},"functions":[{"cyclomatic":1,"cyclomaticDensity":33.333,"halstead":{"bugs":0.038,"difficulty":4,"effort":453.199,"length":29,"time":25.178,"vocabulary":15,"volume":113.3,"operands":{"distinct":9,"total":12,"identifiers":["__stripped__"]},"operators":{"distinct":6,"total":17,"identifiers":["__stripped__"]}},"params":1,"sloc":{"logical":3,"physical":6},"errors":[],"lineEnd":27,"lineStart":22,"name":"constructor","complexity":{"cyclomatic":1,"sloc":{"logical":3,"physical":6},"halstead":{"bugs":0.038,"difficulty":4,"effort":453.199,"length":29,"time":25.178,"vocabulary":15,"volume":113.3,"operands":{"distinct":9,"total":12,"identifiers":["__stripped__"]},"operators":{"distinct":6,"total":17,"identifiers":["__stripped__"]}}},"line":22},{"cyclomatic":3,"cyclomaticDensity":60,"halstead":{"bugs":0.043,"difficulty":9.375,"effort":1211.884,"length":31,"time":67.327,"vocabulary":18,"volume":129.268,"operands":{"distinct":8,"total":15,"identifiers":["__stripped__"]},"operators":{"distinct":10,"total":16,"identifiers":["__stripped__"]}},"params":1,"sloc":{"logical":5,"physical":7},"errors":[],"lineEnd":35,"lineStart":29,"name":"parseUrl","complexity":{"cyclomatic":3,"sloc":{"logical":5,"physical":7},"halstead":{"bugs":0.043,"difficulty":9.375,"effort":1211.884,"length":31,"time":67.327,"vocabulary":18,"volume":129.268,"operands":{"distinct":8,"total":15,"identifiers":["__stripped__"]},"operators":{"distinct":10,"total":16,"identifiers":["__stripped__"]}}},"line":29},{"cyclomatic":2,"cyclomaticDensity":22.222,"halstead":{"bugs":0.145,"difficulty":7.308,"effort":3173.539,"length":84,"time":176.308,"vocabulary":36,"volume":434.274,"operands":{"distinct":26,"total":38,"identifiers":["__stripped__"]},"operators":{"distinct":10,"total":46,"identifiers":["__stripped__"]}},"params":0,"sloc":{"logical":9,"physical":40},"errors":[],"lineEnd":76,"lineStart":37,"name":"render","complexity":{"cyclomatic":2,"sloc":{"logical":9,"physical":40},"halstead":{"bugs":0.145,"difficulty":7.308,"effort":3173.539,"length":84,"time":176.308,"vocabulary":36,"volume":434.274,"operands":{"distinct":26,"total":38,"identifiers":["__stripped__"]},"operators":{"distinct":10,"total":46,"identifiers":["__stripped__"]}}},"line":37},{"cyclomatic":1,"cyclomaticDensity":0,"halstead":{"bugs":0.006,"difficulty":2,"effort":36.189,"length":7,"time":2.011,"vocabulary":6,"volume":18.095,"operands":{"distinct":3,"total":4,"identifiers":["__stripped__"]},"operators":{"distinct":3,"total":3,"identifiers":["__stripped__"]}},"params":2,"sloc":{"logical":0,"physical":1},"errors":[],"lineEnd":54,"lineStart":54,"name":"<anonymous>","complexity":{"cyclomatic":1,"sloc":{"logical":0,"physical":1},"halstead":{"bugs":0.006,"difficulty":2,"effort":36.189,"length":7,"time":2.011,"vocabulary":6,"volume":18.095,"operands":{"distinct":3,"total":4,"identifiers":["__stripped__"]},"operators":{"distinct":3,"total":3,"identifiers":["__stripped__"]}}},"line":54}]},"eslint":{"messages":[]}}